{
    "errors": [],
    "get": "players/",
    "parameters": {
        "season": "2021",
        "team": "1"
    },
    "response": [
        {
            "affiliation": "South Gwinnett HS (GA)/USA",
            "birth": {
                "country": "USA",
                "date": "1986-10-27"
            },
            "college": "South Gwinnett HS (GA)",
            "firstname": "Lou",
            "height": {
                "feets": "6",
                "inches": "2",
                "meters": "1.88"
            },
            "id": 553,
            "lastname": "Williams",
            "leagues": {
                "standard": {
                    "active": true,
                    "jersey": 6,
                    "pos": "G"
                }
            },
            "nba": {
                "pro": 16,
                "start": 2005
            },
            "weight": {
                "kilograms": "79.4",
                "pounds": "175"
            }
        },
        {
            "affiliation": null,
            "birth": {
                "country": null,
                "date": null
            },
            "college": null,
            "firstname": "Jahlil",
            "height": {
                "feets": null,
                "inches": null,
                "meters": null
            },
            "id": 402,
            "lastname": "Okafor",
            "leagues": {
                "standard": {
                    "active": false,
                    "jersey": 14,
                    "pos": null
                }
            },
            "nba": {
                "pro": 0,
                "start": 0
            },
            "weight": {
                "kilograms": null,
                "pounds": null
            }
        },
        {
            "affiliation": "Utah/USA",
            "birth": {
                "country": "USA",
                "date": "1992-04-26"
            },
            "college": "Utah",
            "firstname": "Delon",
            "height": {
                "feets": "6",
                "inches": "5",
                "meters": "1.96"
            },
            "id": 564,
            "lastname": "Wright",
            "leagues": {
                "standard": {
                    "active": true,
                    "jersey": 55,
                    "pos": "G"
                }
            },
            "nba": {
                "pro": 6,
                "start": 2015
            },
            "weight": {
                "kilograms": "83.9",
                "pounds": "185"
            }
        },
        {
            "affiliation": "North Carolina State/USA",
            "birth": {
                "country": "USA",
                "date": "1994-07-25"
            },
            "college": "North Carolina State",
            "firstname": "Cat",
            "height": {
                "feets": null,
                "inches": null,
                "meters": null
            },
            "id": 588,
            "lastname": "Barber",
            "leagues": {
                "standard": {
                    "active": false,
                    "jersey": 5,
                    "pos": null
                }
            },
            "nba": {
                "pro": 0,
                "start": 2021
            },
            "weight": {
                "kilograms": null,
                "pounds": null
            }
        },
        {
            "affiliation": "Mega Basket/France",
            "birth": {
                "country": "France",
                "date": "1995-05-09"
            },
            "college": "Mega Basket",
            "firstname": "Timothe",
            "height": {
                "feets": "6",
                "inches": "7",
                "meters": "2.01"
            },
            "id": 329,
            "lastname": "Luwawu-Cabarrot",
            "leagues": {
                "africa": {
                    "active": true,
                    "jersey": null,
                    "pos": "G-F"
                },
                "standard": {
                    "active": true,
                    "jersey": 7,
                    "pos": "G-F"
                }
            },
            "nba": {
                "pro": 5,
                "start": 2016
            },
            "weight": {
                "kilograms": "97.5",
                "pounds": "215"
            }
        },
        {
            "affiliation": "Wake Forest/USA",
            "birth": {
                "country": "USA",
                "date": "1997-09-23"
            },
            "college": "Wake Forest",
            "firstname": "John",
            "height": {
                "feets": "6",
                "inches": "9",
                "meters": "2.06"
            },
            "id": 761,
            "lastname": "Collins",
            "leagues": {
                "africa": {
                    "active": true,
                    "jersey": 20,
                    "pos": "F-C"
                },
                "standard": {
                    "active": true,
                    "jersey": 20,
                    "pos": "F-C"
                },
                "utah": {
                    "active": true,
                    "jersey": 20,
                    "pos": "F-C"
                },
                "vegas": {
                    "active": true,
                    "jersey": 20,
                    "pos": "F-C"
                }
            },
            "nba": {
                "pro": 4,
                "start": 2017
            },
            "weight": {
                "kilograms": "102.5",
                "pounds": "226"
            }
        },
        {
            "affiliation": "Oregon/USA",
            "birth": {
                "country": "USA",
                "date": "1995-01-07"
            },
            "college": "Oregon",
            "firstname": "Jordan",
            "height": {
                "feets": "6",
                "inches": "7",
                "meters": "2.01"
            },
            "id": 738,
            "lastname": "Bell",
            "leagues": {
                "sacramento": {
                    "active": true,
                    "jersey": 2,
                    "pos": "F"
                },
                "standard": {
                    "active": true,
                    "jersey": 20,
                    "pos": "F"
                },
                "vegas": {
                    "active": true,
                    "jersey": 24,
                    "pos": "F"
                }
            },
            "nba": {
                "pro": 4,
                "start": 2017
            },
            "weight": {
                "kilograms": "98.0",
                "pounds": "216"
            }
        },
        {
            "affiliation": "Kansas State/USA",
            "birth": {
                "country": "USA",
                "date": "1994-12-20"
            },
            "college": "Kansas State",
            "firstname": "Wes",
            "height": {
                "feets": null,
                "inches": null,
                "meters": null
            },
            "id": 802,
            "lastname": "Iwundu",
            "leagues": {
                "standard": {
                    "active": true,
                    "jersey": 4,
                    "pos": "F"
                },
                "vegas": {
                    "active": true,
                    "jersey": 25,
                    "pos": "F"
                }
            },
            "nba": {
                "pro": 0,
                "start": 2017
            },
            "weight": {
                "kilograms": null,
                "pounds": null
            }
        },
        {
            "affiliation": "Nevada/USA",
            "birth": {
                "country": "USA",
                "date": "1996-07-11"
            },
            "college": "Nevada",
            "firstname": "Cameron",
            "height": {
                "feets": "6",
                "inches": "8",
                "meters": "2.03"
            },
            "id": 1011,
            "lastname": "Oliver",
            "leagues": {
                "sacramento": {
                    "active": true,
                    "jersey": 27,
                    "pos": "F"
                },
                "standard": {
                    "active": true,
                    "jersey": 21,
                    "pos": "F"
                },
                "vegas": {
                    "active": true,
                    "jersey": 27,
                    "pos": "F"
                }
            },
            "nba": {
                "pro": 1,
                "start": 2020
            },
            "weight": {
                "kilograms": "108.4",
                "pounds": "239"
            }
        },
        {
            "affiliation": "Maryland/USA",
            "birth": {
                "country": "USA",
                "date": "1998-08-27"
            },
            "college": "Maryland",
            "firstname": "Kevin",
            "height": {
                "feets": "6",
                "inches": "7",
                "meters": "2.01"
            },
            "id": 980,
            "lastname": "Huerter",
            "leagues": {
                "standard": {
                    "active": true,
                    "jersey": 9,
                    "pos": "G-F"
                },
                "utah": {
                    "active": true,
                    "jersey": 1,
                    "pos": "G"
                },
                "vegas": {
                    "active": true,
                    "jersey": 1,
                    "pos": "G"
                }
            },
            "nba": {
                "pro": 3,
                "start": 2018
            },
            "weight": {
                "kilograms": "89.8",
                "pounds": "198"
            }
        },
        {
            "affiliation": "Kentucky/USA",
            "birth": {
                "country": "USA",
                "date": "1999-08-11"
            },
            "college": "Kentucky",
            "firstname": "Kevin",
            "height": {
                "feets": "6",
                "inches": "7",
                "meters": "2.01"
            },
            "id": 987,
            "lastname": "Knox II",
            "leagues": {
                "standard": {
                    "active": true,
                    "jersey": 5,
                    "pos": "F"
                },
                "vegas": {
                    "active": true,
                    "jersey": 20,
                    "pos": "F"
                }
            },
            "nba": {
                "pro": 3,
                "start": 2018
            },
            "weight": {
                "kilograms": "97.5",
                "pounds": "215"
            }
        },
        {
            "affiliation": "Oklahoma/USA",
            "birth": {
                "country": "USA",
                "date": "1998-09-19"
            },
            "college": "Oklahoma",
            "firstname": "Trae",
            "height": {
                "feets": "6",
                "inches": "1",
                "meters": "1.85"
            },
            "id": 1046,
            "lastname": "Young",
            "leagues": {
                "standard": {
                    "active": true,
                    "jersey": 11,
                    "pos": "G"
                },
                "utah": {
                    "active": true,
                    "jersey": 11,
                    "pos": "G"
                },
                "vegas": {
                    "active": true,
                    "jersey": 11,
                    "pos": "G"
                }
            },
            "nba": {
                "pro": 3,
                "start": 2018
            },
            "weight": {
                "kilograms": "74.4",
                "pounds": "164"
            }
        },
        {
            "affiliation": null,
            "birth": {
                "country": null,
                "date": null
            },
            "college": null,
            "firstname": "Johnny",
            "height": {
                "feets": null,
                "inches": null,
                "meters": null
            },
            "id": 977,
            "lastname": "Hamilton",
            "leagues": {
                "standard": {
                    "active": false,
                    "jersey": 24,
                    "pos": null
                },
                "vegas": {
                    "active": true,
                    "jersey": 49,
                    "pos": "C"
                }
            },
            "nba": {
                "pro": 0,
                "start": 0
            },
            "weight": {
                "kilograms": null,
                "pounds": null
            }
        },
        {
            "affiliation": null,
            "birth": {
                "country": null,
                "date": null
            },
            "college": null,
            "firstname": "DeVaughn",
            "height": {
                "feets": null,
                "inches": null,
                "meters": null
            },
            "id": 923,
            "lastname": "Akoon-Purcell",
            "leagues": {
                "standard": {
                    "active": false,
                    "jersey": 44,
                    "pos": null
                },
                "vegas": {
                    "active": true,
                    "jersey": 42,
                    "pos": "F"
                }
            },
            "nba": {
                "pro": 0,
                "start": 0
            },
            "weight": {
                "kilograms": null,
                "pounds": null
            }
        },
        {
            "affiliation": null,
            "birth": {
                "country": null,
                "date": null
            },
            "college": null,
            "firstname": "Justin",
            "height": {
                "feets": null,
                "inches": null,
                "meters": null
            },
            "id": 2211,
            "lastname": "Tillman",
            "leagues": {
                "standard": {
                    "active": true,
                    "jersey": null,
                    "pos": "F"
                },
                "vegas": {
                    "active": true,
                    "jersey": 64,
                    "pos": "F"
                }
            },
            "nba": {
                "pro": 0,
                "start": 0
            },
            "weight": {
                "kilograms": null,
                "pounds": null
            }
        },
        {
            "affiliation": null,
            "birth": {
                "country": null,
                "date": null
            },
            "college": null,
            "firstname": "Chris",
            "height": {
                "feets": null,
                "inches": null,
                "meters": null
            },
            "id": 2165,
            "lastname": "Clemons",
            "leagues": {
                "standard": {
                    "active": false,
                    "jersey": 39,
                    "pos": null
                },
                "vegas": {
                    "active": true,
                    "jersey": 39,
                    "pos": "G"
                }
            },
            "nba": {
                "pro": 0,
                "start": 0
            },
            "weight": {
                "kilograms": null,
                "pounds": null
            }
        },
        {
            "affiliation": "Duke/USA",
            "birth": {
                "country": "USA",
                "date": "1998-04-07"
            },
            "college": "Duke",
            "firstname": "Javin",
            "height": {
                "feets": "6",
                "inches": "10",
                "meters": "2.08"
            },
            "id": 2579,
            "lastname": "DeLaurier",
            "leagues": {
                "standard": {
                    "active": true,
                    "jersey": 12,
                    "pos": "C"
                },
                "vegas": {
                    "active": true,
                    "jersey": 40,
                    "pos": "F-C"
                }
            },
            "nba": {
                "pro": 0,
                "start": 0
            },
            "weight": {
                "kilograms": "106.1",
                "pounds": "234"
            }
        },
        {
            "affiliation": "Tulsa/USA",
            "birth": {
                "country": "USA",
                "date": "1997-08-30"
            },
            "college": "Tulsa",
            "firstname": "DaQuan",
            "height": {
                "feets": "6",
                "inches": "5",
                "meters": "1.96"
            },
            "id": 1948,
            "lastname": "Jeffries",
            "leagues": {
                "standard": {
                    "active": true,
                    "jersey": 8,
                    "pos": "G-F"
                },
                "utah": {
                    "active": true,
                    "jersey": 55,
                    "pos": "G-F"
                },
                "vegas": {
                    "active": true,
                    "jersey": 16,
                    "pos": "F"
                }
            },
            "nba": {
                "pro": 3,
                "start": 2019
            },
            "weight": {
                "kilograms": "102.1",
                "pounds": "225"
            }
        },
        {
            "affiliation": "Duke/USA",
            "birth": {
                "country": "USA",
                "date": "1999-09-01"
            },
            "college": "Duke",
            "firstname": "Cam",
            "height": {
                "feets": "6",
                "inches": "8",
                "meters": "2.03"
            },
            "id": 1889,
            "lastname": "Reddish",
            "leagues": {
                "standard": {
                    "active": true,
                    "jersey": null,
                    "pos": "F-G"
                }
            },
            "nba": {
                "pro": 2,
                "start": 2019
            },
            "weight": {
                "kilograms": "98.4",
                "pounds": "217"
            }
        },
        {
            "affiliation": "Virginia/USA",
            "birth": {
                "country": "USA",
                "date": "1997-12-02"
            },
            "college": "Virginia",
            "firstname": "De'Andre",
            "height": {
                "feets": "6",
                "inches": "8",
                "meters": "2.03"
            },
            "id": 1868,
            "lastname": "Hunter",
            "leagues": {
                "standard": {
                    "active": true,
                    "jersey": 12,
                    "pos": "F-G"
                },
                "vegas": {
                    "active": true,
                    "jersey": 12,
                    "pos": "F"
                }
            },
            "nba": {
                "pro": 2,
                "start": 2019
            },
            "weight": {
                "kilograms": "100.2",
                "pounds": "221"
            }
        },
        {
            "affiliation": "Tennessee/United Kingdom",
            "birth": {
                "country": "United Kingdom",
                "date": "1997-03-30"
            },
            "college": "Tennessee",
            "firstname": "Admiral",
            "height": {
                "feets": "6",
                "inches": "5",
                "meters": "1.96"
            },
            "id": 1892,
            "lastname": "Schofield",
            "leagues": {
                "standard": {
                    "active": true,
                    "jersey": 25,
                    "pos": "F"
                },
                "vegas": {
                    "active": true,
                    "jersey": 25,
                    "pos": "F"
                }
            },
            "nba": {
                "pro": 1,
                "start": 2019
            },
            "weight": {
                "kilograms": "109.3",
                "pounds": "241"
            }
        },
        {
            "affiliation": "Memphis/USA",
            "birth": {
                "country": "USA",
                "date": "1996-06-19"
            },
            "college": "Memphis",
            "firstname": "Jeremiah",
            "height": {
                "feets": "6",
                "inches": "2",
                "meters": "1.88"
            },
            "id": 2388,
            "lastname": "Martin",
            "leagues": {
                "standard": {
                    "active": true,
                    "jersey": 3,
                    "pos": "G"
                },
                "vegas": {
                    "active": true,
                    "jersey": 10,
                    "pos": "G"
                }
            },
            "nba": {
                "pro": 2,
                "start": 2019
            },
            "weight": {
                "kilograms": "83.9",
                "pounds": "185"
            }
        },
        {
            "affiliation": "Southern California/USA",
            "birth": {
                "country": "USA",
                "date": "2000-12-11"
            },
            "college": "Southern California",
            "firstname": "Onyeka",
            "height": {
                "feets": "6",
                "inches": "8",
                "meters": "2.03"
            },
            "id": 2629,
            "lastname": "Okongwu",
            "leagues": {
                "standard": {
                    "active": true,
                    "jersey": 17,
                    "pos": "F-C"
                }
            },
            "nba": {
                "pro": 1,
                "start": 2020
            },
            "weight": {
                "kilograms": "108.9",
                "pounds": "240"
            }
        },
        {
            "affiliation": "Louisiana State/USA",
            "birth": {
                "country": "USA",
                "date": "1997-09-05"
            },
            "college": "Louisiana State",
            "firstname": "Skylar",
            "height": {
                "feets": "6",
                "inches": "4",
                "meters": "1.93"
            },
            "id": 2620,
            "lastname": "Mays",
            "leagues": {
                "standard": {
                    "active": true,
                    "jersey": 4,
                    "pos": "G"
                },
                "vegas": {
                    "active": true,
                    "jersey": 4,
                    "pos": "G"
                }
            },
            "nba": {
                "pro": 1,
                "start": 2020
            },
            "weight": {
                "kilograms": "93.0",
                "pounds": "205"
            }
        },
        {
            "affiliation": "Washington/USA",
            "birth": {
                "country": "USA",
                "date": "1999-08-24"
            },
            "college": "Washington",
            "firstname": "Nahziah",
            "height": {
                "feets": "6",
                "inches": "6",
                "meters": "1.98"
            },
            "id": 2979,
            "lastname": "Carter",
            "leagues": {
                "vegas": {
                    "active": true,
                    "jersey": 31,
                    "pos": "G"
                }
            },
            "nba": {
                "pro": 0,
                "start": 0
            },
            "weight": {
                "kilograms": "93.0",
                "pounds": "205"
            }
        },
        {
            "affiliation": "Auburn/USA",
            "birth": {
                "country": "USA",
                "date": "2001-06-11"
            },
            "college": "Auburn",
            "firstname": "Sharife",
            "height": {
                "feets": "6",
                "inches": "1",
                "meters": "1.85"
            },
            "id": 2800,
            "lastname": "Cooper",
            "leagues": {
                "standard": {
                    "active": true,
                    "jersey": 2,
                    "pos": "G"
                },
                "vegas": {
                    "active": true,
                    "jersey": 2,
                    "pos": "G"
                }
            },
            "nba": {
                "pro": 0,
                "start": 2021
            },
            "weight": {
                "kilograms": "79.8",
                "pounds": "176"
            }
        },
        {
            "affiliation": "Duke/USA",
            "birth": {
                "country": "USA",
                "date": "2001-12-18"
            },
            "college": "Duke",
            "firstname": "Jalen",
            "height": {
                "feets": "6",
                "inches": "8",
                "meters": "2.03"
            },
            "id": 2819,
            "lastname": "Johnson",
            "leagues": {
                "standard": {
                    "active": true,
                    "jersey": 1,
                    "pos": "F"
                },
                "vegas": {
                    "active": true,
                    "jersey": 1,
                    "pos": "F"
                }
            },
            "nba": {
                "pro": 0,
                "start": 2021
            },
            "weight": {
                "kilograms": "99.3",
                "pounds": "219"
            }
        },
        {
            "affiliation": "Michigan/USA",
            "birth": {
                "country": "USA",
                "date": "1998-12-04"
            },
            "college": "Michigan",
            "firstname": "Chaundee",
            "height": {
                "feets": "6",
                "inches": "5",
                "meters": "1.96"
            },
            "id": 2794,
            "lastname": "Brown Jr.",
            "leagues": {
                "sacramento": {
                    "active": true,
                    "jersey": 15,
                    "pos": "G"
                },
                "standard": {
                    "active": true,
                    "jersey": 38,
                    "pos": "F"
                },
                "vegas": {
                    "active": true,
                    "jersey": 45,
                    "pos": "G"
                }
            },
            "nba": {
                "pro": 0,
                "start": 2021
            },
            "weight": {
                "kilograms": "97.5",
                "pounds": "215"
            }
        },
        {
            "affiliation": "South Carolina/Canada",
            "birth": {
                "country": "Canada",
                "date": "2000-07-15"
            },
            "college": "South Carolina",
            "firstname": "A.J.",
            "height": {
                "feets": "6",
                "inches": "6",
                "meters": "1.98"
            },
            "id": 2890,
            "lastname": "Lawson",
            "leagues": {
                "sacramento": {
                    "active": true,
                    "jersey": 58,
                    "pos": "G"
                },
                "standard": {
                    "active": true,
                    "jersey": 5,
                    "pos": "G"
                },
                "vegas": {
                    "active": true,
                    "jersey": 29,
                    "pos": "G"
                }
            },
            "nba": {
                "pro": 0,
                "start": 0
            },
            "weight": {
                "kilograms": "81.6",
                "pounds": "180"
            }
        },
        {
            "affiliation": null,
            "birth": {
                "country": null,
                "date": null
            },
            "college": null,
            "firstname": "Malik",
            "height": {
                "feets": null,
                "inches": null,
                "meters": null
            },
            "id": 3395,
            "lastname": "Ellison",
            "leagues": {
                "standard": {
                    "active": true,
                    "jersey": null,
                    "pos": "G"
                },
                "utah": {
                    "active": true,
                    "jersey": 28,
                    "pos": "G"
                },
                "vegas": {
                    "active": true,
                    "jersey": 28,
                    "pos": "G"
                }
            },
            "nba": {
                "pro": 0,
                "start": 0
            },
            "weight": {
                "kilograms": null,
                "pounds": null
            }
        },
        {
            "affiliation": "Illinois/USA",
            "birth": {
                "country": "USA",
                "date": "1995-10-26"
            },
            "college": "Illinois",
            "firstname": "Malcolm",
            "height": {
                "feets": "6",
                "inches": "6",
                "meters": "1.98"
            },
            "id": 3380,
            "lastname": "Hill",
            "leagues": {
                "standard": {
                    "active": true,
                    "jersey": 14,
                    "pos": "F"
                },
                "vegas": {
                    "active": true,
                    "jersey": 21,
                    "pos": "G-F"
                }
            },
            "nba": {
                "pro": 0,
                "start": 2021
            },
            "weight": {
                "kilograms": "99.8",
                "pounds": "220"
            }
        },
        {
            "affiliation": null,
            "birth": {
                "country": null,
                "date": null
            },
            "college": null,
            "firstname": "Ibi",
            "height": {
                "feets": null,
                "inches": null,
                "meters": null
            },
            "id": 3382,
            "lastname": "Watson-Boye",
            "leagues": {
                "standard": {
                    "active": false,
                    "jersey": 16,
                    "pos": null
                }
            },
            "nba": {
                "pro": 0,
                "start": 0
            },
            "weight": {
                "kilograms": null,
                "pounds": null
            }
        },
        {
            "affiliation": "Olimpia Milano/Italy",
            "birth": {
                "country": "Italy",
                "date": "1988-08-08"
            },
            "college": "Olimpia Milano",
            "firstname": "Danilo",
            "height": {
                "feets": "6",
                "inches": "10",
                "meters": "2.08"
            },
            "id": 181,
            "lastname": "Gallinari",
            "leagues": {
                "africa": {
                    "active": true,
                    "jersey": 8,
                    "pos": "F"
                },
                "standard": {
                    "active": true,
                    "jersey": 8,
                    "pos": "F"
                }
            },
            "nba": {
                "pro": 12,
                "start": 2008
            },
            "weight": {
                "kilograms": "107.0",
                "pounds": "236"
            }
        },
        {
            "affiliation": "Cincinnati/USA",
            "birth": {
                "country": "USA",
                "date": "1990-09-05"
            },
            "college": "Cincinnati",
            "firstname": "Lance",
            "height": {
                "feets": "6",
                "inches": "5",
                "meters": "1.96"
            },
            "id": 497,
            "lastname": "Stephenson",
            "leagues": {
                "standard": {
                    "active": true,
                    "jersey": 6,
                    "pos": "F"
                }
            },
            "nba": {
                "pro": 9,
                "start": 2010
            },
            "weight": {
                "kilograms": "95.3",
                "pounds": "210"
            }
        },
        {
            "affiliation": "Louisville/Senegal",
            "birth": {
                "country": "Senegal",
                "date": "1990-01-18"
            },
            "college": "Louisville",
            "firstname": "Gorgui",
            "height": {
                "feets": "6",
                "inches": "10",
                "meters": "2.08"
            },
            "id": 141,
            "lastname": "Dieng",
            "leagues": {
                "standard": {
                    "active": true,
                    "jersey": 10,
                    "pos": "C"
                }
            },
            "nba": {
                "pro": 8,
                "start": 2013
            },
            "weight": {
                "kilograms": "112.5",
                "pounds": "248"
            }
        },
        {
            "affiliation": "Arizona/USA",
            "birth": {
                "country": "USA",
                "date": "1991-03-18"
            },
            "college": "Arizona",
            "firstname": "Solomon",
            "height": {
                "feets": null,
                "inches": null,
                "meters": null
            },
            "id": 239,
            "lastname": "Hill",
            "leagues": {
                "standard": {
                    "active": false,
                    "jersey": 99,
                    "pos": null
                }
            },
            "nba": {
                "pro": 0,
                "start": 2013
            },
            "weight": {
                "kilograms": null,
                "pounds": null
            }
        },
        {
            "affiliation": null,
            "birth": {
                "country": null,
                "date": null
            },
            "college": null,
            "firstname": "Eric",
            "height": {
                "feets": null,
                "inches": null,
                "meters": null
            },
            "id": 372,
            "lastname": "Moreland",
            "leagues": {
                "standard": {
                    "active": false,
                    "jersey": 25,
                    "pos": null
                },
                "vegas": {
                    "active": true,
                    "jersey": 25,
                    "pos": "F"
                }
            },
            "nba": {
                "pro": 0,
                "start": 0
            },
            "weight": {
                "kilograms": null,
                "pounds": null
            }
        },
        {
            "affiliation": "Elan Chalon/Switzerland",
            "birth": {
                "country": "Switzerland",
                "date": "1994-05-18"
            },
            "college": "Elan Chalon",
            "firstname": "Clint",
            "height": {
                "feets": "6",
                "inches": "10",
                "meters": "2.08"
            },
            "id": 92,
            "lastname": "Capela",
            "leagues": {
                "standard": {
                    "active": true,
                    "jersey": 15,
                    "pos": "C"
                }
            },
            "nba": {
                "pro": 7,
                "start": 2014
            },
            "weight": {
                "kilograms": "116.1",
                "pounds": "256"
            }
        },
        {
            "affiliation": "Fenerbahce/Serbia",
            "birth": {
                "country": "Serbia",
                "date": "1992-08-18"
            },
            "college": "Fenerbahce",
            "firstname": "Bogdan",
            "height": {
                "feets": "6",
                "inches": "6",
                "meters": "1.98"
            },
            "id": 743,
            "lastname": "Bogdanovic",
            "leagues": {
                "standard": {
                    "active": true,
                    "jersey": 13,
                    "pos": "G"
                }
            },
            "nba": {
                "pro": 4,
                "start": 2017
            },
            "weight": {
                "kilograms": "102.1",
                "pounds": "225"
            }
        },
        {
            "affiliation": null,
            "birth": {
                "country": null,
                "date": "1997-12-22"
            },
            "college": "Notre Dame",
            "firstname": "Juwan",
            "height": {
                "feets": "6",
                "inches": "11",
                "meters": "2.11"
            },
            "id": 3006,
            "lastname": "Durham",
            "leagues": {
                "vegas": {
                    "active": true,
                    "jersey": 30,
                    "pos": "F"
                }
            },
            "nba": {
                "pro": 0,
                "start": 0
            },
            "weight": {
                "kilograms": "104.8",
                "pounds": "231"
            }
        },
        {
            "affiliation": "California-Santa Barbara/USA",
            "birth": {
                "country": "USA",
                "date": "1997-06-05"
            },
            "college": "California-Santa Barbara",
            "firstname": "Max",
            "height": {
                "feets": "6",
                "inches": "3",
                "meters": "1.9"
            },
            "id": 3057,
            "lastname": "Heidegger",
            "leagues": {
                "vegas": {
                    "active": true,
                    "jersey": 26,
                    "pos": "G"
                }
            },
            "nba": {
                "pro": 0,
                "start": 0
            },
            "weight": {
                "kilograms": "81.6",
                "pounds": "180"
            }
        },
        {
            "affiliation": null,
            "birth": {
                "country": null,
                "date": "1999-06-21"
            },
            "college": "Lafayette",
            "firstname": "Justin",
            "height": {
                "feets": "6",
                "inches": "3",
                "meters": "1.9"
            },
            "id": 3072,
            "lastname": "Jaworski",
            "leagues": {
                "vegas": {
                    "active": true,
                    "jersey": 33,
                    "pos": "G"
                }
            },
            "nba": {
                "pro": 0,
                "start": 0
            },
            "weight": {
                "kilograms": "88.9",
                "pounds": "196"
            }
        },
        {
            "affiliation": null,
            "birth": {
                "country": null,
                "date": "1998-01-06"
            },
            "college": "Dayton",
            "firstname": "Ibi",
            "height": {
                "feets": "6",
                "inches": "5",
                "meters": "1.96"
            },
            "id": 3263,
            "lastname": "Watson",
            "leagues": {
                "vegas": {
                    "active": true,
                    "jersey": 16,
                    "pos": "G"
                }
            },
            "nba": {
                "pro": 0,
                "start": 0
            },
            "weight": {
                "kilograms": "90.7",
                "pounds": "200"
            }
        }
    ],
    "results": 43
}