{
    "errors": [],
    "get": "players/",
    "parameters": {
        "season": "2022",
        "team": "4"
    },
    "response": [
        {
            "affiliation": "Baylor/USA",
            "birth": {
                "country": "USA",
                "date": "1993-06-05"
            },
            "college": "Baylor",
            "firstname": "Royce",
            "height": {
                "feets": "6",
                "inches": "5",
                "meters": "1.96"
            },
            "id": 851,
            "lastname": "O'Neale",
            "leagues": {
                "standard": {
                    "active": true,
                    "jersey": null,
                    "pos": "F"
                }
            },
            "nba": {
                "pro": 4,
                "start": 2017
            },
            "weight": {
                "kilograms": "102.5",
                "pounds": "226"
            }
        },
        {
            "affiliation": "Louisiana State/Australia",
            "birth": {
                "country": "Australia",
                "date": "1996-07-20"
            },
            "college": "Louisiana State",
            "firstname": "Ben",
            "height": {
                "feets": "6",
                "inches": "11",
                "meters": "2.11"
            },
            "id": 481,
            "lastname": "Simmons",
            "leagues": {
                "standard": {
                    "active": true,
                    "jersey": 10,
                    "pos": "G-F"
                }
            },
            "nba": {
                "pro": 4,
                "start": 2017
            },
            "weight": {
                "kilograms": "108.9",
                "pounds": "240"
            }
        },
        {
            "affiliation": "Florida/USA",
            "birth": {
                "country": "USA",
                "date": "1993-05-04"
            },
            "college": "Florida",
            "firstname": "Dorian",
            "height": {
                "feets": "6",
                "inches": "7",
                "meters": "2.01"
            },
            "id": 175,
            "lastname": "Finney-Smith",
            "leagues": {
                "standard": {
                    "active": true,
                    "jersey": 10,
                    "pos": "F"
                },
                "vegas": {
                    "active": true,
                    "jersey": 10,
                    "pos": "F"
                }
            },
            "nba": {
                "pro": 5,
                "start": 2016
            },
            "weight": {
                "kilograms": "99.8",
                "pounds": "220"
            }
        },
        {
            "affiliation": null,
            "birth": {
                "country": null,
                "date": null
            },
            "college": null,
            "firstname": "Edmond",
            "height": {
                "feets": null,
                "inches": null,
                "meters": null
            },
            "id": 880,
            "lastname": "Sumner",
            "leagues": {
                "standard": {
                    "active": true,
                    "jersey": 4,
                    "pos": "G"
                },
                "vegas": {
                    "active": true,
                    "jersey": 5,
                    "pos": "G"
                }
            },
            "nba": {
                "pro": 0,
                "start": 0
            },
            "weight": {
                "kilograms": null,
                "pounds": null
            }
        },
        {
            "affiliation": "Villanova/USA",
            "birth": {
                "country": "USA",
                "date": "1996-08-30"
            },
            "college": "Villanova",
            "firstname": "Mikal",
            "height": {
                "feets": "6",
                "inches": "6",
                "meters": "1.98"
            },
            "id": 940,
            "lastname": "Bridges",
            "leagues": {
                "standard": {
                    "active": true,
                    "jersey": 25,
                    "pos": "F"
                },
                "vegas": {
                    "active": true,
                    "jersey": 25,
                    "pos": "F"
                }
            },
            "nba": {
                "pro": 3,
                "start": 2018
            },
            "weight": {
                "kilograms": "94.8",
                "pounds": "209"
            }
        },
        {
            "affiliation": "George Washington/Japan",
            "birth": {
                "country": "Japan",
                "date": "1994-10-13"
            },
            "college": "George Washington",
            "firstname": "Yuta",
            "height": {
                "feets": "6",
                "inches": "9",
                "meters": "2.06"
            },
            "id": 1040,
            "lastname": "Watanabe",
            "leagues": {
                "standard": {
                    "active": true,
                    "jersey": 18,
                    "pos": "G-F"
                },
                "utah": {
                    "active": true,
                    "jersey": 18,
                    "pos": "F"
                },
                "vegas": {
                    "active": true,
                    "jersey": 18,
                    "pos": "F"
                }
            },
            "nba": {
                "pro": 3,
                "start": 2018
            },
            "weight": {
                "kilograms": "97.5",
                "pounds": "215"
            }
        },
        {
            "affiliation": "Florida/USA",
            "birth": {
                "country": "USA",
                "date": "1995-11-21"
            },
            "college": "Florida",
            "firstname": "Chris",
            "height": {
                "feets": "5",
                "inches": "11",
                "meters": "1.8"
            },
            "id": 1069,
            "lastname": "Chiozza",
            "leagues": {
                "standard": {
                    "active": true,
                    "jersey": 2,
                    "pos": "G"
                },
                "vegas": {
                    "active": true,
                    "jersey": 2,
                    "pos": "G"
                }
            },
            "nba": {
                "pro": 3,
                "start": 2018
            },
            "weight": {
                "kilograms": "79.4",
                "pounds": "175"
            }
        },
        {
            "affiliation": null,
            "birth": {
                "country": null,
                "date": null
            },
            "college": null,
            "firstname": "Moses",
            "height": {
                "feets": null,
                "inches": null,
                "meters": null
            },
            "id": 2160,
            "lastname": "Brown",
            "leagues": {
                "standard": {
                    "active": true,
                    "jersey": 6,
                    "pos": "C"
                },
                "vegas": {
                    "active": true,
                    "jersey": 56,
                    "pos": "C"
                }
            },
            "nba": {
                "pro": 0,
                "start": 0
            },
            "weight": {
                "kilograms": null,
                "pounds": null
            }
        },
        {
            "affiliation": "Georgia/USA",
            "birth": {
                "country": "USA",
                "date": "1999-04-17"
            },
            "college": "Georgia",
            "firstname": "Nic",
            "height": {
                "feets": "6",
                "inches": "11",
                "meters": "2.11"
            },
            "id": 1854,
            "lastname": "Claxton",
            "leagues": {
                "standard": {
                    "active": true,
                    "jersey": 33,
                    "pos": "C"
                },
                "vegas": {
                    "active": true,
                    "jersey": 33,
                    "pos": "F-C"
                }
            },
            "nba": {
                "pro": 2,
                "start": 2019
            },
            "weight": {
                "kilograms": "97.5",
                "pounds": "215"
            }
        },
        {
            "affiliation": "North Carolina/USA",
            "birth": {
                "country": "USA",
                "date": "1996-03-03"
            },
            "college": "North Carolina",
            "firstname": "Cameron",
            "height": {
                "feets": "6",
                "inches": "8",
                "meters": "2.03"
            },
            "id": 1871,
            "lastname": "Johnson",
            "leagues": {
                "standard": {
                    "active": true,
                    "jersey": 23,
                    "pos": "F"
                }
            },
            "nba": {
                "pro": 2,
                "start": 2019
            },
            "weight": {
                "kilograms": "95.3",
                "pounds": "210"
            }
        },
        {
            "affiliation": "North Carolina/USA",
            "birth": {
                "country": "USA",
                "date": "2001-11-06"
            },
            "college": "North Carolina",
            "firstname": "Day'Ron",
            "height": {
                "feets": "6",
                "inches": "9",
                "meters": "2.06"
            },
            "id": 2848,
            "lastname": "Sharpe",
            "leagues": {
                "standard": {
                    "active": true,
                    "jersey": 20,
                    "pos": "C"
                },
                "vegas": {
                    "active": true,
                    "jersey": 20,
                    "pos": "C"
                }
            },
            "nba": {
                "pro": 0,
                "start": 2021
            },
            "weight": {
                "kilograms": "120.2",
                "pounds": "265"
            }
        },
        {
            "affiliation": "Pepperdine/USA",
            "birth": {
                "country": "USA",
                "date": "2000-08-09"
            },
            "college": "Pepperdine",
            "firstname": "Kessler",
            "height": {
                "feets": "6",
                "inches": "7",
                "meters": "2.01"
            },
            "id": 2805,
            "lastname": "Edwards",
            "leagues": {
                "standard": {
                    "active": true,
                    "jersey": 14,
                    "pos": "F"
                },
                "vegas": {
                    "active": true,
                    "jersey": 14,
                    "pos": "F"
                }
            },
            "nba": {
                "pro": 0,
                "start": 2021
            },
            "weight": {
                "kilograms": "92.1",
                "pounds": "203"
            }
        },
        {
            "affiliation": "Louisiana State/Japan",
            "birth": {
                "country": "Japan",
                "date": "2001-10-13"
            },
            "college": "Louisiana State",
            "firstname": "Cam",
            "height": {
                "feets": "6",
                "inches": "3",
                "meters": "1.9"
            },
            "id": 2855,
            "lastname": "Thomas",
            "leagues": {
                "standard": {
                    "active": true,
                    "jersey": 24,
                    "pos": "G"
                },
                "vegas": {
                    "active": true,
                    "jersey": 24,
                    "pos": "G"
                }
            },
            "nba": {
                "pro": 0,
                "start": 2021
            },
            "weight": {
                "kilograms": "95.3",
                "pounds": "210"
            }
        },
        {
            "affiliation": "Providence/USA",
            "birth": {
                "country": "USA",
                "date": "1999-10-13"
            },
            "college": "Providence",
            "firstname": "David",
            "height": {
                "feets": "6",
                "inches": "4",
                "meters": "1.93"
            },
            "id": 2804,
            "lastname": "Duke Jr.",
            "leagues": {
                "standard": {
                    "active": true,
                    "jersey": 6,
                    "pos": "G"
                },
                "vegas": {
                    "active": true,
                    "jersey": 6,
                    "pos": "G"
                }
            },
            "nba": {
                "pro": 0,
                "start": 2021
            },
            "weight": {
                "kilograms": "92.5",
                "pounds": "204"
            }
        },
        {
            "affiliation": null,
            "birth": {
                "country": null,
                "date": null
            },
            "college": null,
            "firstname": "RaiQuan",
            "height": {
                "feets": null,
                "inches": null,
                "meters": null
            },
            "id": 2809,
            "lastname": "Gray",
            "leagues": {
                "standard": {
                    "active": true,
                    "jersey": null,
                    "pos": "F"
                },
                "vegas": {
                    "active": true,
                    "jersey": 4,
                    "pos": "F"
                }
            },
            "nba": {
                "pro": 0,
                "start": 0
            },
            "weight": {
                "kilograms": null,
                "pounds": null
            }
        },
        {
            "affiliation": null,
            "birth": {
                "country": null,
                "date": null
            },
            "college": null,
            "firstname": "Dru",
            "height": {
                "feets": null,
                "inches": null,
                "meters": null
            },
            "id": 3360,
            "lastname": "Smith",
            "leagues": {
                "standard": {
                    "active": true,
                    "jersey": 9,
                    "pos": "G"
                },
                "vegas": {
                    "active": true,
                    "jersey": 9,
                    "pos": "G"
                }
            },
            "nba": {
                "pro": 0,
                "start": 0
            },
            "weight": {
                "kilograms": null,
                "pounds": null
            }
        },
        {
            "affiliation": null,
            "birth": {
                "country": null,
                "date": null
            },
            "college": null,
            "firstname": "Alondes",
            "height": {
                "feets": null,
                "inches": null,
                "meters": null
            },
            "id": 3503,
            "lastname": "Williams",
            "leagues": {
                "standard": {
                    "active": true,
                    "jersey": 31,
                    "pos": "G"
                },
                "vegas": {
                    "active": true,
                    "jersey": 31,
                    "pos": "G"
                }
            },
            "nba": {
                "pro": 0,
                "start": 0
            },
            "weight": {
                "kilograms": null,
                "pounds": null
            }
        },
        {
            "affiliation": "Texas/USA",
            "birth": {
                "country": "USA",
                "date": "1988-09-29"
            },
            "college": "Texas",
            "firstname": "Kevin",
            "height": {
                "feets": "6",
                "inches": "10",
                "meters": "2.08"
            },
            "id": 153,
            "lastname": "Durant",
            "leagues": {
                "standard": {
                    "active": true,
                    "jersey": 7,
                    "pos": "F"
                }
            },
            "nba": {
                "pro": 13,
                "start": 2007
            },
            "weight": {
                "kilograms": "108.9",
                "pounds": "240"
            }
        },
        {
            "affiliation": "St. Mary's/Australia",
            "birth": {
                "country": "Australia",
                "date": "1988-08-11"
            },
            "college": "St. Mary's",
            "firstname": "Patty",
            "height": {
                "feets": "6",
                "inches": "0",
                "meters": "1.83"
            },
            "id": 365,
            "lastname": "Mills",
            "leagues": {
                "standard": {
                    "active": true,
                    "jersey": 8,
                    "pos": "G"
                }
            },
            "nba": {
                "pro": 12,
                "start": 2009
            },
            "weight": {
                "kilograms": "81.6",
                "pounds": "180"
            }
        },
        {
            "affiliation": "Duke/Australia",
            "birth": {
                "country": "Australia",
                "date": "1992-03-23"
            },
            "college": "Duke",
            "firstname": "Kyrie",
            "height": {
                "feets": "6",
                "inches": "2",
                "meters": "1.88"
            },
            "id": 261,
            "lastname": "Irving",
            "leagues": {
                "standard": {
                    "active": true,
                    "jersey": 11,
                    "pos": "G"
                }
            },
            "nba": {
                "pro": 10,
                "start": 2011
            },
            "weight": {
                "kilograms": "88.5",
                "pounds": "195"
            }
        },
        {
            "affiliation": "Kansas/USA",
            "birth": {
                "country": "USA",
                "date": "1989-09-02"
            },
            "college": "Kansas",
            "firstname": "Markieff",
            "height": {
                "feets": "6",
                "inches": "9",
                "meters": "2.06"
            },
            "id": 374,
            "lastname": "Morris",
            "leagues": {
                "standard": {
                    "active": true,
                    "jersey": 13,
                    "pos": "F"
                }
            },
            "nba": {
                "pro": 10,
                "start": 2011
            },
            "weight": {
                "kilograms": "111.1",
                "pounds": "245"
            }
        },
        {
            "affiliation": "Kentucky/USA",
            "birth": {
                "country": "USA",
                "date": "1994-04-10"
            },
            "college": "Kentucky",
            "firstname": "Nerlens",
            "height": {
                "feets": "6",
                "inches": "11",
                "meters": "2.11"
            },
            "id": 394,
            "lastname": "Noel",
            "leagues": {
                "standard": {
                    "active": true,
                    "jersey": 3,
                    "pos": "C-F"
                }
            },
            "nba": {
                "pro": 7,
                "start": 2014
            },
            "weight": {
                "kilograms": "99.8",
                "pounds": "220"
            }
        },
        {
            "affiliation": "Duke/USA",
            "birth": {
                "country": "USA",
                "date": "1990-08-23"
            },
            "college": "Duke",
            "firstname": "Seth",
            "height": {
                "feets": "6",
                "inches": "2",
                "meters": "1.88"
            },
            "id": 123,
            "lastname": "Curry",
            "leagues": {
                "standard": {
                    "active": true,
                    "jersey": 30,
                    "pos": "G"
                }
            },
            "nba": {
                "pro": 7,
                "start": 2013
            },
            "weight": {
                "kilograms": "83.9",
                "pounds": "185"
            }
        },
        {
            "affiliation": "Colorado/USA",
            "birth": {
                "country": "USA",
                "date": "1993-04-06"
            },
            "college": "Colorado",
            "firstname": "Spencer",
            "height": {
                "feets": "6",
                "inches": "6",
                "meters": "1.98"
            },
            "id": 142,
            "lastname": "Dinwiddie",
            "leagues": {
                "standard": {
                    "active": true,
                    "jersey": 26,
                    "pos": "G"
                }
            },
            "nba": {
                "pro": 7,
                "start": 2014
            },
            "weight": {
                "kilograms": "97.5",
                "pounds": "215"
            }
        },
        {
            "affiliation": "Virginia/USA",
            "birth": {
                "country": "USA",
                "date": "1991-09-06"
            },
            "college": "Virginia",
            "firstname": "Joe",
            "height": {
                "feets": "6",
                "inches": "6",
                "meters": "1.98"
            },
            "id": 221,
            "lastname": "Harris",
            "leagues": {
                "standard": {
                    "active": true,
                    "jersey": 12,
                    "pos": "G-F"
                }
            },
            "nba": {
                "pro": 7,
                "start": 2014
            },
            "weight": {
                "kilograms": "99.8",
                "pounds": "220"
            }
        },
        {
            "affiliation": "North Carolina State/USA",
            "birth": {
                "country": "USA",
                "date": "1993-09-05"
            },
            "college": "North Carolina State",
            "firstname": "T.J.",
            "height": {
                "feets": "6",
                "inches": "8",
                "meters": "2.03"
            },
            "id": 540,
            "lastname": "Warren",
            "leagues": {
                "standard": {
                    "active": true,
                    "jersey": 1,
                    "pos": "F"
                }
            },
            "nba": {
                "pro": 7,
                "start": 2014
            },
            "weight": {
                "kilograms": "99.8",
                "pounds": "220"
            }
        }
    ],
    "results": 26
}