{
    "errors": [],
    "get": "players/",
    "parameters": {
        "season": "2015",
        "team": "10"
    },
    "response": [
        {
            "affiliation": null,
            "birth": {
                "country": null,
                "date": null
            },
            "college": null,
            "firstname": "Ersan",
            "height": {
                "feets": null,
                "inches": null,
                "meters": null
            },
            "id": 257,
            "lastname": "Ilyasova",
            "leagues": {
                "standard": {
                    "active": false,
                    "jersey": 77,
                    "pos": null
                }
            },
            "nba": {
                "pro": 0,
                "start": 0
            },
            "weight": {
                "kilograms": null,
                "pounds": null
            }
        },
        {
            "affiliation": "Arizona/USA",
            "birth": {
                "country": "USA",
                "date": "1996-05-29"
            },
            "college": "Arizona",
            "firstname": "Stanley",
            "height": {
                "feets": "6",
                "inches": "6",
                "meters": "1.98"
            },
            "id": 276,
            "lastname": "Johnson",
            "leagues": {
                "standard": {
                    "active": true,
                    "jersey": 3,
                    "pos": "F-G"
                }
            },
            "nba": {
                "pro": 6,
                "start": 2015
            },
            "weight": {
                "kilograms": "109.8",
                "pounds": "242"
            }
        },
        {
            "affiliation": null,
            "birth": {
                "country": null,
                "date": null
            },
            "college": null,
            "firstname": "Darrun",
            "height": {
                "feets": null,
                "inches": null,
                "meters": null
            },
            "id": 240,
            "lastname": "Hilliard",
            "leagues": {
                "standard": {
                    "active": true,
                    "jersey": 24,
                    "pos": "F"
                }
            },
            "nba": {
                "pro": 0,
                "start": 0
            },
            "weight": {
                "kilograms": null,
                "pounds": null
            }
        },
        {
            "affiliation": "UNLV/Canada",
            "birth": {
                "country": "Canada",
                "date": "1982-08-09"
            },
            "college": "Nevada-Las Vegas",
            "firstname": "Joel",
            "height": {
                "feets": "6",
                "inches": "9",
                "meters": "2.06"
            },
            "id": 22,
            "lastname": "Anthony",
            "leagues": {
                "standard": {
                    "active": false,
                    "jersey": 30,
                    "pos": "C"
                }
            },
            "nba": {
                "pro": 9,
                "start": 2007
            },
            "weight": {
                "kilograms": "111.1",
                "pounds": "245"
            }
        },
        {
            "affiliation": null,
            "birth": {
                "country": null,
                "date": null
            },
            "college": null,
            "firstname": "Anthony",
            "height": {
                "feets": null,
                "inches": null,
                "meters": null
            },
            "id": 517,
            "lastname": "Tolliver",
            "leagues": {
                "standard": {
                    "active": false,
                    "jersey": 43,
                    "pos": null
                }
            },
            "nba": {
                "pro": 0,
                "start": 0
            },
            "weight": {
                "kilograms": null,
                "pounds": null
            }
        },
        {
            "affiliation": "Oak Hill Academy (Mouth of Wilson, VA)/USA",
            "birth": {
                "country": "USA",
                "date": "1989-09-23"
            },
            "college": "Oak Hill Academy (VA)",
            "firstname": "Brandon",
            "height": {
                "feets": "6",
                "inches": "1",
                "meters": "1.85"
            },
            "id": 269,
            "lastname": "Jennings",
            "leagues": {
                "standard": {
                    "active": true,
                    "jersey": 11,
                    "pos": "G"
                }
            },
            "nba": {
                "pro": 9,
                "start": 2009
            },
            "weight": {
                "kilograms": "77.1",
                "pounds": "170"
            }
        },
        {
            "affiliation": null,
            "birth": {
                "country": null,
                "date": null
            },
            "college": null,
            "firstname": "Jodie",
            "height": {
                "feets": null,
                "inches": null,
                "meters": null
            },
            "id": 358,
            "lastname": "Meeks",
            "leagues": {
                "standard": {
                    "active": true,
                    "jersey": 20,
                    "pos": "G"
                }
            },
            "nba": {
                "pro": 0,
                "start": 0
            },
            "weight": {
                "kilograms": null,
                "pounds": null
            }
        },
        {
            "affiliation": "Kansas/USA",
            "birth": {
                "country": "USA",
                "date": "1989-09-02"
            },
            "college": "Kansas",
            "firstname": "Marcus",
            "height": {
                "feets": "6",
                "inches": "8",
                "meters": "2.03"
            },
            "id": 373,
            "lastname": "Morris Sr.",
            "leagues": {
                "standard": {
                    "active": true,
                    "jersey": 8,
                    "pos": "F"
                }
            },
            "nba": {
                "pro": 10,
                "start": 2011
            },
            "weight": {
                "kilograms": "98.9",
                "pounds": "218"
            }
        },
        {
            "affiliation": "Tennessee/USA",
            "birth": {
                "country": "USA",
                "date": "1992-07-15"
            },
            "college": "Tennessee",
            "firstname": "Tobias",
            "height": {
                "feets": "6",
                "inches": "7",
                "meters": "2.01"
            },
            "id": 222,
            "lastname": "Harris",
            "leagues": {
                "standard": {
                    "active": true,
                    "jersey": 12,
                    "pos": "F"
                }
            },
            "nba": {
                "pro": 10,
                "start": 2011
            },
            "weight": {
                "kilograms": "102.5",
                "pounds": "226"
            }
        },
        {
            "affiliation": "Boston College/USA",
            "birth": {
                "country": "USA",
                "date": "1990-04-16"
            },
            "college": "Boston College",
            "firstname": "Reggie",
            "height": {
                "feets": "6",
                "inches": "2",
                "meters": "1.88"
            },
            "id": 264,
            "lastname": "Jackson",
            "leagues": {
                "standard": {
                    "active": true,
                    "jersey": 1,
                    "pos": "G"
                }
            },
            "nba": {
                "pro": 10,
                "start": 2011
            },
            "weight": {
                "kilograms": "94.3",
                "pounds": "208"
            }
        },
        {
            "affiliation": "Richmond/USA",
            "birth": {
                "country": "USA",
                "date": "1989-08-30"
            },
            "college": "Richmond",
            "firstname": "Justin",
            "height": {
                "feets": null,
                "inches": null,
                "meters": null
            },
            "id": 1700,
            "lastname": "Harper",
            "leagues": {
                "vegas": {
                    "active": false,
                    "jersey": 40,
                    "pos": null
                }
            },
            "nba": {
                "pro": 0,
                "start": 2011
            },
            "weight": {
                "kilograms": null,
                "pounds": null
            }
        },
        {
            "affiliation": "Connecticut/USA",
            "birth": {
                "country": "USA",
                "date": "1993-08-10"
            },
            "college": "Connecticut",
            "firstname": "Andre",
            "height": {
                "feets": "6",
                "inches": "10",
                "meters": "2.08"
            },
            "id": 147,
            "lastname": "Drummond",
            "leagues": {
                "standard": {
                    "active": true,
                    "jersey": 3,
                    "pos": "C"
                }
            },
            "nba": {
                "pro": 9,
                "start": 2012
            },
            "weight": {
                "kilograms": "126.6",
                "pounds": "279"
            }
        },
        {
            "affiliation": "Washington State/Australia",
            "birth": {
                "country": "Australia",
                "date": "1986-12-09"
            },
            "college": "Washington State",
            "firstname": "Aron",
            "height": {
                "feets": "6",
                "inches": "10",
                "meters": "2.08"
            },
            "id": 42,
            "lastname": "Baynes",
            "leagues": {
                "standard": {
                    "active": true,
                    "jersey": 46,
                    "pos": "C-F"
                }
            },
            "nba": {
                "pro": 8,
                "start": 2012
            },
            "weight": {
                "kilograms": "117.9",
                "pounds": "260"
            }
        },
        {
            "affiliation": "Georgia/USA",
            "birth": {
                "country": "USA",
                "date": "1993-02-18"
            },
            "college": "Georgia",
            "firstname": "Kentavious",
            "height": {
                "feets": "6",
                "inches": "5",
                "meters": "1.96"
            },
            "id": 89,
            "lastname": "Caldwell-Pope",
            "leagues": {
                "standard": {
                    "active": true,
                    "jersey": 5,
                    "pos": "G"
                }
            },
            "nba": {
                "pro": 8,
                "start": 2013
            },
            "weight": {
                "kilograms": "92.5",
                "pounds": "204"
            }
        },
        {
            "affiliation": "North Carolina State/USA",
            "birth": {
                "country": "USA",
                "date": "1990-08-26"
            },
            "college": "North Carolina State",
            "firstname": "Lorenzo",
            "height": {
                "feets": "6",
                "inches": "5",
                "meters": "1.96"
            },
            "id": 76,
            "lastname": "Brown",
            "leagues": {
                "standard": {
                    "active": true,
                    "jersey": 4,
                    "pos": "G"
                }
            },
            "nba": {
                "pro": 4,
                "start": 2013
            },
            "weight": {
                "kilograms": "85.7",
                "pounds": "189"
            }
        },
        {
            "affiliation": "North Carolina/USA",
            "birth": {
                "country": "USA",
                "date": "1991-03-16"
            },
            "college": "North Carolina",
            "firstname": "Reggie",
            "height": {
                "feets": "6",
                "inches": "6",
                "meters": "1.98"
            },
            "id": 82,
            "lastname": "Bullock",
            "leagues": {
                "standard": {
                    "active": true,
                    "jersey": 25,
                    "pos": "G-F"
                }
            },
            "nba": {
                "pro": 8,
                "start": 2013
            },
            "weight": {
                "kilograms": "93.0",
                "pounds": "205"
            }
        },
        {
            "affiliation": null,
            "birth": {
                "country": null,
                "date": null
            },
            "college": null,
            "firstname": "Adonis",
            "height": {
                "feets": null,
                "inches": null,
                "meters": null
            },
            "id": 2030,
            "lastname": "Thomas",
            "leagues": {
                "vegas": {
                    "active": true,
                    "jersey": 4,
                    "pos": "F"
                }
            },
            "nba": {
                "pro": 0,
                "start": 0
            },
            "weight": {
                "kilograms": null,
                "pounds": null
            }
        },
        {
            "affiliation": "Campbell",
            "birth": {
                "country": " ",
                "date": "1990-05-26"
            },
            "college": "Campbell",
            "firstname": "Eric",
            "height": {
                "feets": "6",
                "inches": "8",
                "meters": "2.03"
            },
            "id": 1404,
            "lastname": "Griffin",
            "leagues": {
                "standard": {
                    "active": false,
                    "jersey": 24,
                    "pos": null
                },
                "vegas": {
                    "active": true,
                    "jersey": 39,
                    "pos": "F"
                }
            },
            "nba": {
                "pro": 4,
                "start": 0
            },
            "weight": {
                "kilograms": "88.0",
                "pounds": "194"
            }
        },
        {
            "affiliation": "Colorado/USA",
            "birth": {
                "country": "USA",
                "date": "1993-04-06"
            },
            "college": "Colorado",
            "firstname": "Spencer",
            "height": {
                "feets": "6",
                "inches": "6",
                "meters": "1.98"
            },
            "id": 142,
            "lastname": "Dinwiddie",
            "leagues": {
                "standard": {
                    "active": true,
                    "jersey": 26,
                    "pos": "G"
                }
            },
            "nba": {
                "pro": 7,
                "start": 2014
            },
            "weight": {
                "kilograms": "97.5",
                "pounds": "215"
            }
        },
        {
            "affiliation": null,
            "birth": {
                "country": "USA",
                "date": "1980-02-26"
            },
            "college": "Maryland",
            "firstname": "Steve",
            "height": {
                "feets": "6",
                "inches": "3",
                "meters": "1.9"
            },
            "id": 57,
            "lastname": "Blake",
            "leagues": {
                "standard": {
                    "active": false,
                    "jersey": 22,
                    "pos": "G"
                }
            },
            "nba": {
                "pro": 12,
                "start": 2003
            },
            "weight": {
                "kilograms": "78.0",
                "pounds": "172"
            }
        }
    ],
    "results": 20
}