{
    "errors": [],
    "get": "players/",
    "parameters": {
        "season": "2024",
        "team": "17"
    },
    "response": [
        {
            "affiliation": "Ohio State/USA",
            "birth": {
                "country": "USA",
                "date": "1996-02-23"
            },
            "college": "Ohio State",
            "firstname": "D'Angelo",
            "height": {
                "feets": "6",
                "inches": "4",
                "meters": "1.93"
            },
            "id": 462,
            "lastname": "Russell",
            "leagues": {
                "standard": {
                    "active": true,
                    "jersey": null,
                    "pos": "G"
                }
            },
            "nba": {
                "pro": 6,
                "start": 2015
            },
            "weight": {
                "kilograms": "87.5",
                "pounds": "193"
            }
        },
        {
            "affiliation": "Florida/USA",
            "birth": {
                "country": "USA",
                "date": "1993-05-04"
            },
            "college": "Florida",
            "firstname": "Dorian",
            "height": {
                "feets": "6",
                "inches": "7",
                "meters": "2.01"
            },
            "id": 175,
            "lastname": "Finney-Smith",
            "leagues": {
                "standard": {
                    "active": true,
                    "jersey": 10,
                    "pos": "F"
                },
                "vegas": {
                    "active": true,
                    "jersey": 10,
                    "pos": "F"
                }
            },
            "nba": {
                "pro": 5,
                "start": 2016
            },
            "weight": {
                "kilograms": "99.8",
                "pounds": "220"
            }
        },
        {
            "affiliation": "Southern Methodist/USA",
            "birth": {
                "country": "USA",
                "date": "1996-09-26"
            },
            "college": "Southern Methodist",
            "firstname": "Shake",
            "height": {
                "feets": "6",
                "inches": "5",
                "meters": "1.96"
            },
            "id": 1001,
            "lastname": "Milton",
            "leagues": {
                "standard": {
                    "active": true,
                    "jersey": 18,
                    "pos": "G-F"
                },
                "vegas": {
                    "active": true,
                    "jersey": 18,
                    "pos": "G"
                }
            },
            "nba": {
                "pro": 3,
                "start": 2018
            },
            "weight": {
                "kilograms": "93.0",
                "pounds": "205"
            }
        },
        {
            "affiliation": "Gonzaga/Japan",
            "birth": {
                "country": "Japan",
                "date": "1998-02-08"
            },
            "college": "Gonzaga",
            "firstname": "Rui",
            "height": {
                "feets": "6",
                "inches": "8",
                "meters": "2.03"
            },
            "id": 1862,
            "lastname": "Hachimura",
            "leagues": {
                "standard": {
                    "active": true,
                    "jersey": 8,
                    "pos": "F"
                },
                "vegas": {
                    "active": true,
                    "jersey": 8,
                    "pos": "F"
                }
            },
            "nba": {
                "pro": 2,
                "start": 2019
            },
            "weight": {
                "kilograms": "104.3",
                "pounds": "230"
            }
        },
        {
            "affiliation": "California-Santa Barbara/USA",
            "birth": {
                "country": "USA",
                "date": "1996-06-14"
            },
            "college": "California-Santa Barbara",
            "firstname": "Gabe",
            "height": {
                "feets": "6",
                "inches": "3",
                "meters": "1.9"
            },
            "id": 1775,
            "lastname": "Vincent",
            "leagues": {
                "sacramento": {
                    "active": true,
                    "jersey": 2,
                    "pos": "G"
                },
                "standard": {
                    "active": true,
                    "jersey": 2,
                    "pos": "G"
                },
                "vegas": {
                    "active": true,
                    "jersey": 2,
                    "pos": "G"
                }
            },
            "nba": {
                "pro": 2,
                "start": 2019
            },
            "weight": {
                "kilograms": "90.7",
                "pounds": "200"
            }
        },
        {
            "affiliation": "Duke/USA",
            "birth": {
                "country": "USA",
                "date": "1999-09-01"
            },
            "college": "Duke",
            "firstname": "Cam",
            "height": {
                "feets": "6",
                "inches": "8",
                "meters": "2.03"
            },
            "id": 1889,
            "lastname": "Reddish",
            "leagues": {
                "standard": {
                    "active": true,
                    "jersey": null,
                    "pos": "F-G"
                }
            },
            "nba": {
                "pro": 2,
                "start": 2019
            },
            "weight": {
                "kilograms": "98.4",
                "pounds": "217"
            }
        },
        {
            "affiliation": "Texas/USA",
            "birth": {
                "country": "USA",
                "date": "2000-05-23"
            },
            "college": "Texas",
            "firstname": "Jaxson",
            "height": {
                "feets": "6",
                "inches": "11",
                "meters": "2.11"
            },
            "id": 1864,
            "lastname": "Hayes",
            "leagues": {
                "standard": {
                    "active": true,
                    "jersey": 10,
                    "pos": "C-F"
                },
                "vegas": {
                    "active": true,
                    "jersey": 10,
                    "pos": "F-C"
                }
            },
            "nba": {
                "pro": 2,
                "start": 2019
            },
            "weight": {
                "kilograms": "99.8",
                "pounds": "220"
            }
        },
        {
            "affiliation": null,
            "birth": {
                "country": null,
                "date": "1997-08-26"
            },
            "college": " ",
            "firstname": "Kylor",
            "height": {
                "feets": null,
                "inches": null,
                "meters": null
            },
            "id": 2670,
            "lastname": "Kelley",
            "leagues": {
                "standard": {
                    "active": true,
                    "jersey": null,
                    "pos": null
                }
            },
            "nba": {
                "pro": 0,
                "start": 0
            },
            "weight": {
                "kilograms": null,
                "pounds": " "
            }
        },
        {
            "affiliation": "Oklahoma/USA",
            "birth": {
                "country": "USA",
                "date": "1998-05-29"
            },
            "college": "Oklahoma",
            "firstname": "Austin",
            "height": {
                "feets": "6",
                "inches": "5",
                "meters": "1.96"
            },
            "id": 2845,
            "lastname": "Reaves",
            "leagues": {
                "sacramento": {
                    "active": true,
                    "jersey": 31,
                    "pos": "G"
                },
                "standard": {
                    "active": true,
                    "jersey": 15,
                    "pos": "G"
                },
                "vegas": {
                    "active": true,
                    "jersey": 31,
                    "pos": "G"
                }
            },
            "nba": {
                "pro": 0,
                "start": 2021
            },
            "weight": {
                "kilograms": "89.4",
                "pounds": "197"
            }
        },
        {
            "affiliation": "St. Louis/USA",
            "birth": {
                "country": "USA",
                "date": "1998-10-23"
            },
            "college": "St. Louis",
            "firstname": "Jordan",
            "height": {
                "feets": null,
                "inches": null,
                "meters": null
            },
            "id": 3341,
            "lastname": "Goodwin",
            "leagues": {
                "standard": {
                    "active": true,
                    "jersey": 7,
                    "pos": "G"
                },
                "vegas": {
                    "active": true,
                    "jersey": 7,
                    "pos": "G"
                }
            },
            "nba": {
                "pro": 0,
                "start": 2021
            },
            "weight": {
                "kilograms": null,
                "pounds": null
            }
        },
        {
            "affiliation": null,
            "birth": {
                "country": null,
                "date": null
            },
            "college": null,
            "firstname": "Max",
            "height": {
                "feets": null,
                "inches": null,
                "meters": null
            },
            "id": 3427,
            "lastname": "Christie",
            "leagues": {
                "sacramento": {
                    "active": true,
                    "jersey": 10,
                    "pos": "G"
                },
                "standard": {
                    "active": true,
                    "jersey": 10,
                    "pos": "G"
                },
                "vegas": {
                    "active": true,
                    "jersey": 10,
                    "pos": "G"
                }
            },
            "nba": {
                "pro": 0,
                "start": 0
            },
            "weight": {
                "kilograms": null,
                "pounds": null
            }
        },
        {
            "affiliation": null,
            "birth": {
                "country": null,
                "date": null
            },
            "college": null,
            "firstname": "Christian",
            "height": {
                "feets": null,
                "inches": null,
                "meters": null
            },
            "id": 3458,
            "lastname": "Koloko",
            "leagues": {
                "standard": {
                    "active": true,
                    "jersey": 35,
                    "pos": "C"
                },
                "vegas": {
                    "active": true,
                    "jersey": 35,
                    "pos": "C"
                }
            },
            "nba": {
                "pro": 0,
                "start": 0
            },
            "weight": {
                "kilograms": null,
                "pounds": null
            }
        },
        {
            "affiliation": null,
            "birth": {
                "country": null,
                "date": null
            },
            "college": "Florida",
            "firstname": "Colin",
            "height": {
                "feets": "6",
                "inches": null,
                "meters": null
            },
            "id": 3987,
            "lastname": "Castleton",
            "leagues": {
                "standard": {
                    "active": true,
                    "jersey": 14,
                    "pos": "C"
                }
            },
            "nba": {
                "pro": 0,
                "start": 0
            },
            "weight": {
                "kilograms": null,
                "pounds": "231"
            }
        },
        {
            "affiliation": null,
            "birth": {
                "country": null,
                "date": null
            },
            "college": "Indiana",
            "firstname": "Jalen",
            "height": {
                "feets": "6",
                "inches": null,
                "meters": null
            },
            "id": 3990,
            "lastname": "HoodSchifino",
            "leagues": {
                "standard": {
                    "active": true,
                    "jersey": null,
                    "pos": "G"
                }
            },
            "nba": {
                "pro": 0,
                "start": 0
            },
            "weight": {
                "kilograms": null,
                "pounds": "215"
            }
        },
        {
            "affiliation": null,
            "birth": {
                "country": null,
                "date": null
            },
            "college": "Pepperdine",
            "firstname": "Maxwell",
            "height": {
                "feets": "6",
                "inches": null,
                "meters": null
            },
            "id": 3991,
            "lastname": "Lewis",
            "leagues": {
                "standard": {
                    "active": true,
                    "jersey": 21,
                    "pos": "F"
                }
            },
            "nba": {
                "pro": 0,
                "start": 0
            },
            "weight": {
                "kilograms": null,
                "pounds": "205"
            }
        },
        {
            "affiliation": null,
            "birth": {
                "country": null,
                "date": null
            },
            "college": "USC",
            "firstname": "Bronny",
            "height": {
                "feets": "6",
                "inches": null,
                "meters": null
            },
            "id": 4125,
            "lastname": "James",
            "leagues": {
                "standard": {
                    "active": true,
                    "jersey": 9,
                    "pos": "G"
                }
            },
            "nba": {
                "pro": 0,
                "start": 0
            },
            "weight": {
                "kilograms": null,
                "pounds": "210"
            }
        },
        {
            "affiliation": null,
            "birth": {
                "country": null,
                "date": null
            },
            "college": "Tennessee",
            "firstname": "Dalton",
            "height": {
                "feets": "6",
                "inches": null,
                "meters": null
            },
            "id": 4126,
            "lastname": "Knecht",
            "leagues": {
                "standard": {
                    "active": true,
                    "jersey": 4,
                    "pos": "G"
                }
            },
            "nba": {
                "pro": 0,
                "start": 0
            },
            "weight": {
                "kilograms": null,
                "pounds": "204"
            }
        },
        {
            "affiliation": null,
            "birth": {
                "country": null,
                "date": null
            },
            "college": "Xavier",
            "firstname": "Quincy",
            "height": {
                "feets": "6",
                "inches": null,
                "meters": null
            },
            "id": 4127,
            "lastname": "Olivari",
            "leagues": {
                "standard": {
                    "active": true,
                    "jersey": null,
                    "pos": "G"
                }
            },
            "nba": {
                "pro": 0,
                "start": 0
            },
            "weight": {
                "kilograms": null,
                "pounds": "200"
            }
        },
        {
            "affiliation": null,
            "birth": {
                "country": null,
                "date": null
            },
            "college": null,
            "firstname": "Armel",
            "height": {
                "feets": "6",
                "inches": null,
                "meters": null
            },
            "id": 4128,
            "lastname": "Traore",
            "leagues": {
                "standard": {
                    "active": true,
                    "jersey": 37,
                    "pos": "F"
                }
            },
            "nba": {
                "pro": 0,
                "start": 0
            },
            "weight": {
                "kilograms": null,
                "pounds": "210"
            }
        },
        {
            "affiliation": "Kentucky/USA",
            "birth": {
                "country": "USA",
                "date": "1993-03-11"
            },
            "college": "Kentucky",
            "firstname": "Anthony",
            "height": {
                "feets": "6",
                "inches": "10",
                "meters": "2.08"
            },
            "id": 126,
            "lastname": "Davis",
            "leagues": {
                "standard": {
                    "active": true,
                    "jersey": 3,
                    "pos": "F-C"
                }
            },
            "nba": {
                "pro": 9,
                "start": 2012
            },
            "weight": {
                "kilograms": "114.8",
                "pounds": "253"
            }
        },
        {
            "affiliation": "St. Vincent-St. Mary HS (OH)/USA",
            "birth": {
                "country": "USA",
                "date": "1984-12-30"
            },
            "college": "St. Vincent-St. Mary HS (OH)",
            "firstname": "LeBron",
            "height": {
                "feets": "6",
                "inches": "9",
                "meters": "2.06"
            },
            "id": 265,
            "lastname": "James",
            "leagues": {
                "standard": {
                    "active": true,
                    "jersey": 6,
                    "pos": "F"
                }
            },
            "nba": {
                "pro": 18,
                "start": 2003
            },
            "weight": {
                "kilograms": "113.4",
                "pounds": "250"
            }
        }
    ],
    "results": 21
}