{
    "errors": [],
    "get": "players/",
    "parameters": {
        "season": "2016",
        "team": "29"
    },
    "response": [
        {
            "affiliation": "Notre Dame/USA",
            "birth": {
                "country": "USA",
                "date": "1993-01-06"
            },
            "college": "Notre Dame",
            "firstname": "Pat",
            "height": {
                "feets": "6",
                "inches": "5",
                "meters": "1.96"
            },
            "id": 115,
            "lastname": "Connaughton",
            "leagues": {
                "standard": {
                    "active": true,
                    "jersey": 24,
                    "pos": "G"
                }
            },
            "nba": {
                "pro": 6,
                "start": 2015
            },
            "weight": {
                "kilograms": "94.8",
                "pounds": "209"
            }
        },
        {
            "affiliation": null,
            "birth": {
                "country": "Dominican Republic",
                "date": "1993-04-06"
            },
            "college": "Westchester CC NY",
            "firstname": "Luis",
            "height": {
                "feets": "6",
                "inches": "7",
                "meters": "2.01"
            },
            "id": 370,
            "lastname": "Montero",
            "leagues": {
                "standard": {
                    "active": false,
                    "jersey": 44,
                    "pos": "G"
                }
            },
            "nba": {
                "pro": 0,
                "start": 2015
            },
            "weight": {
                "kilograms": "83.9",
                "pounds": "185"
            }
        },
        {
            "affiliation": "Maryland/USA",
            "birth": {
                "country": "USA",
                "date": "1994-03-07"
            },
            "college": "Maryland",
            "firstname": "Jake",
            "height": {
                "feets": "6",
                "inches": "8",
                "meters": "2.03"
            },
            "id": 310,
            "lastname": "Layman",
            "leagues": {
                "standard": {
                    "active": true,
                    "jersey": 10,
                    "pos": "F"
                },
                "vegas": {
                    "active": true,
                    "jersey": 10,
                    "pos": "F"
                }
            },
            "nba": {
                "pro": 5,
                "start": 2016
            },
            "weight": {
                "kilograms": "94.8",
                "pounds": "209"
            }
        },
        {
            "affiliation": "Louisiana State/USA",
            "birth": {
                "country": "USA",
                "date": "1994-10-27"
            },
            "college": "Louisiana State",
            "firstname": "Tim",
            "height": {
                "feets": "6",
                "inches": "6",
                "meters": "1.98"
            },
            "id": 439,
            "lastname": "Quarterman",
            "leagues": {
                "standard": {
                    "active": false,
                    "jersey": 55,
                    "pos": "G"
                },
                "vegas": {
                    "active": true,
                    "jersey": 55,
                    "pos": "G"
                }
            },
            "nba": {
                "pro": 0,
                "start": 2016
            },
            "weight": {
                "kilograms": "86.2",
                "pounds": "190"
            }
        },
        {
            "affiliation": null,
            "birth": {
                "country": null,
                "date": null
            },
            "college": null,
            "firstname": "Greg",
            "height": {
                "feets": null,
                "inches": null,
                "meters": null
            },
            "id": 684,
            "lastname": "Stiemsma",
            "leagues": {
                "standard": {
                    "active": false,
                    "jersey": 54,
                    "pos": null
                }
            },
            "nba": {
                "pro": 0,
                "start": 0
            },
            "weight": {
                "kilograms": null,
                "pounds": null
            }
        },
        {
            "affiliation": "Ohio State/USA",
            "birth": {
                "country": "USA",
                "date": "1988-10-27"
            },
            "college": "Ohio State",
            "firstname": "Evan",
            "height": {
                "feets": "6",
                "inches": "6",
                "meters": "1.98"
            },
            "id": 521,
            "lastname": "Turner",
            "leagues": {
                "standard": {
                    "active": true,
                    "jersey": 1,
                    "pos": "G-F"
                }
            },
            "nba": {
                "pro": 10,
                "start": 2010
            },
            "weight": {
                "kilograms": "99.8",
                "pounds": "220"
            }
        },
        {
            "affiliation": null,
            "birth": {
                "country": null,
                "date": null
            },
            "college": null,
            "firstname": "Al-Farouq",
            "height": {
                "feets": null,
                "inches": null,
                "meters": null
            },
            "id": 12,
            "lastname": "Aminu",
            "leagues": {
                "africa": {
                    "active": true,
                    "jersey": 8,
                    "pos": "F"
                },
                "standard": {
                    "active": false,
                    "jersey": 72,
                    "pos": null
                }
            },
            "nba": {
                "pro": 0,
                "start": 0
            },
            "weight": {
                "kilograms": null,
                "pounds": null
            }
        },
        {
            "affiliation": "North Carolina/USA",
            "birth": {
                "country": "USA",
                "date": "1989-06-05"
            },
            "college": "North Carolina",
            "firstname": "Ed",
            "height": {
                "feets": "6",
                "inches": "9",
                "meters": "2.06"
            },
            "id": 128,
            "lastname": "Davis",
            "leagues": {
                "standard": {
                    "active": true,
                    "jersey": 21,
                    "pos": "C-F"
                }
            },
            "nba": {
                "pro": 11,
                "start": 2010
            },
            "weight": {
                "kilograms": "98.9",
                "pounds": "218"
            }
        },
        {
            "affiliation": "Weber State/USA",
            "birth": {
                "country": "USA",
                "date": "1990-07-15"
            },
            "college": "Weber State",
            "firstname": "Damian",
            "height": {
                "feets": "6",
                "inches": "2",
                "meters": "1.88"
            },
            "id": 319,
            "lastname": "Lillard",
            "leagues": {
                "standard": {
                    "active": true,
                    "jersey": null,
                    "pos": "G"
                }
            },
            "nba": {
                "pro": 9,
                "start": 2012
            },
            "weight": {
                "kilograms": "88.5",
                "pounds": "195"
            }
        },
        {
            "affiliation": "Illinois/USA",
            "birth": {
                "country": "USA",
                "date": "1992-02-27"
            },
            "college": "Illinois",
            "firstname": "Meyers",
            "height": {
                "feets": null,
                "inches": null,
                "meters": null
            },
            "id": 315,
            "lastname": "Leonard",
            "leagues": {
                "standard": {
                    "active": false,
                    "jersey": 99,
                    "pos": null
                }
            },
            "nba": {
                "pro": 0,
                "start": 2012
            },
            "weight": {
                "kilograms": null,
                "pounds": null
            }
        },
        {
            "affiliation": "St. John's/USA",
            "birth": {
                "country": "USA",
                "date": "1993-05-11"
            },
            "college": "St. John's, N.Y.",
            "firstname": "Maurice",
            "height": {
                "feets": "6",
                "inches": "7",
                "meters": "2.01"
            },
            "id": 217,
            "lastname": "Harkless",
            "leagues": {
                "standard": {
                    "active": false,
                    "jersey": 7,
                    "pos": null
                }
            },
            "nba": {
                "pro": 9,
                "start": 2012
            },
            "weight": {
                "kilograms": "99.8",
                "pounds": "220"
            }
        },
        {
            "affiliation": "Vanderbilt/Nigeria",
            "birth": {
                "country": "Nigeria",
                "date": "1989-10-21"
            },
            "college": "Vanderbilt",
            "firstname": "Festus",
            "height": {
                "feets": "6",
                "inches": "11",
                "meters": "2.11"
            },
            "id": 165,
            "lastname": "Ezeli",
            "leagues": {
                "standard": {
                    "active": false,
                    "jersey": 31,
                    "pos": "C"
                }
            },
            "nba": {
                "pro": 3,
                "start": 2012
            },
            "weight": {
                "kilograms": "120.2",
                "pounds": "265"
            }
        },
        {
            "affiliation": null,
            "birth": {
                "country": null,
                "date": null
            },
            "college": null,
            "firstname": "Allen",
            "height": {
                "feets": null,
                "inches": null,
                "meters": null
            },
            "id": 119,
            "lastname": "Crabbe",
            "leagues": {
                "standard": {
                    "active": false,
                    "jersey": 9,
                    "pos": null
                }
            },
            "nba": {
                "pro": 0,
                "start": 0
            },
            "weight": {
                "kilograms": null,
                "pounds": null
            }
        },
        {
            "affiliation": "Lehigh/USA",
            "birth": {
                "country": "USA",
                "date": "1991-09-19"
            },
            "college": "Lehigh",
            "firstname": "CJ",
            "height": {
                "feets": "6",
                "inches": "3",
                "meters": "1.9"
            },
            "id": 347,
            "lastname": "McCollum",
            "leagues": {
                "standard": {
                    "active": true,
                    "jersey": 3,
                    "pos": "G"
                }
            },
            "nba": {
                "pro": 8,
                "start": 2013
            },
            "weight": {
                "kilograms": "86.2",
                "pounds": "190"
            }
        },
        {
            "affiliation": "Duke/USA",
            "birth": {
                "country": "USA",
                "date": "1990-03-05"
            },
            "college": "Duke",
            "firstname": "Mason",
            "height": {
                "feets": "6",
                "inches": "11",
                "meters": "2.11"
            },
            "id": 426,
            "lastname": "Plumlee",
            "leagues": {
                "standard": {
                    "active": true,
                    "jersey": 24,
                    "pos": "F-C"
                }
            },
            "nba": {
                "pro": 8,
                "start": 2013
            },
            "weight": {
                "kilograms": "115.2",
                "pounds": "254"
            }
        },
        {
            "affiliation": null,
            "birth": {
                "country": null,
                "date": null
            },
            "college": null,
            "firstname": "Grant",
            "height": {
                "feets": null,
                "inches": null,
                "meters": null
            },
            "id": 700,
            "lastname": "Jerrett",
            "leagues": {
                "standard": {
                    "active": false,
                    "jersey": 34,
                    "pos": null
                },
                "vegas": {
                    "active": true,
                    "jersey": 51,
                    "pos": "F-C"
                }
            },
            "nba": {
                "pro": 0,
                "start": 0
            },
            "weight": {
                "kilograms": null,
                "pounds": null
            }
        },
        {
            "affiliation": "Connecticut/USA",
            "birth": {
                "country": "USA",
                "date": "1991-07-14"
            },
            "college": "Connecticut",
            "firstname": "Shabazz",
            "height": {
                "feets": "6",
                "inches": "0",
                "meters": "1.83"
            },
            "id": 386,
            "lastname": "Napier",
            "leagues": {
                "standard": {
                    "active": true,
                    "jersey": 5,
                    "pos": "G"
                }
            },
            "nba": {
                "pro": 6,
                "start": 2014
            },
            "weight": {
                "kilograms": "79.4",
                "pounds": "175"
            }
        },
        {
            "affiliation": null,
            "birth": {
                "country": null,
                "date": null
            },
            "college": null,
            "firstname": "Noah",
            "height": {
                "feets": null,
                "inches": null,
                "meters": null
            },
            "id": 533,
            "lastname": "Vonleh",
            "leagues": {
                "standard": {
                    "active": true,
                    "jersey": 4,
                    "pos": "F"
                }
            },
            "nba": {
                "pro": 0,
                "start": 0
            },
            "weight": {
                "kilograms": null,
                "pounds": null
            }
        },
        {
            "affiliation": "Cedevita/Bosnia and Herzegovina",
            "birth": {
                "country": "Bosnia and Herzegovina",
                "date": "1994-08-23"
            },
            "college": "Cedevita",
            "firstname": "Jusuf",
            "height": {
                "feets": "6",
                "inches": "11",
                "meters": "2.11"
            },
            "id": 398,
            "lastname": "Nurkic",
            "leagues": {
                "standard": {
                    "active": true,
                    "jersey": 27,
                    "pos": "C"
                }
            },
            "nba": {
                "pro": 7,
                "start": 2014
            },
            "weight": {
                "kilograms": "131.5",
                "pounds": "290"
            }
        }
    ],
    "results": 19
}